api.mock-1.0.6.dist-info/DESCRIPTION.rst
api.mock-1.0.6.dist-info/METADATA
api.mock-1.0.6.dist-info/RECORD
api.mock-1.0.6.dist-info/WHEEL
api.mock-1.0.6.dist-info/entry_points.txt
api.mock-1.0.6.dist-info/metadata.json
api.mock-1.0.6.dist-info/top_level.txt
apimock/__init__.py
apimock/device.py
apimock/helper.py
apimock/util.py
