Metadata-Version: 2.0
Name: api.mock
Version: 1.0.6
Summary: A utility of APIMock. (https://github.com/brucezz/APIMock)
Home-page: https://github.com/brucezz/APIMockHelper
Author: Bruce Zheng
Author-email: im.brucezz@gmail.com
License: Apache Software License
Keywords: adb python
Platform: UNKNOWN
Classifier: Development Status :: 4 - Beta
Classifier: Topic :: Utilities
Classifier: License :: OSI Approved :: Apache Software License
Classifier: Programming Language :: Python :: 2.7
Requires-Dist: docopt
Requires-Dist: prettytable
